[
     {
      "posterUrl": "assets/images/episode01.png",
      "title": "Sound waves",
      "guest": "Beep",
      "episode": "1",
      "summary": "Lorem Ipsum is simply dummy text of the printing and typesetting industry.",
      "podcastPath": "assets/audio/file_example_MP3_700KB.mp3"
    },
    {
      "posterUrl": "assets/images/episode02.png",
      "title": "Beep",
      "guest": "Sound waves",
      "episode": "2",
      "summary": "Lorem Ipsum is simply dummy text of the printing and typesetting industry.",
      "podcastPath": "assets/audio/file_example_MP3_700KB.mp3"
    }
  ]
  